geemail/__init__.py
geemail/handler.py
geemail-0.1.3.dist-info/WHEEL
geemail-0.1.3.dist-info/METADATA
geemail-0.1.3.dist-info/RECORD
