Metadata-Version: 1.2
Name: geemail
Version: 0.1.3
Summary: Contains a context manager meant to make it easy to send emails with gmail.
Home-page: https://github.com/knowsuchagency/geemail
License: UNKNOWN
Author: Stephan Fitzpatrick
Author-email: knowsuchagency@gmail.com
Requires-Python: >=2.7
Classifier: License :: OSI Approved :: MIT License
